floip/__init__.py
floip/cli.py
pyfloip-0.0.1.dist-info/DESCRIPTION.rst
pyfloip-0.0.1.dist-info/METADATA
pyfloip-0.0.1.dist-info/RECORD
pyfloip-0.0.1.dist-info/WHEEL
pyfloip-0.0.1.dist-info/entry_points.txt
pyfloip-0.0.1.dist-info/metadata.json
pyfloip-0.0.1.dist-info/top_level.txt
