Metadata-Version: 2.0
Name: pyfloip
Version: 0.0.1
Summary: Converts FLOIP Results data package to XForm
Home-page: https://github.com/onaio/floip-py
Author: Ona Systems LLC
Author-email: tech@ona.io
License: UNKNOWN
Keywords: FLOIP ODK XForm pyxform XLSForm
Platform: UNKNOWN
Classifier: Development Status :: 3 - Alpha
Classifier: Intended Audience :: Developers
Classifier: Topic :: Software Development :: Libraries
Classifier: Programming Language :: Python :: 2.7
Classifier: Programming Language :: Python :: 3.6
Requires-Dist: datapackage
Requires-Dist: pyxform
